Metadata-Version: 1.1
Name: adsbibdesk
Version: 3.2.0
Summary: Add papers from arxiv.org or NASA/SAO ADS to your BibDesk bibliography.
Home-page: http://www.jonathansick.ca/adsbibdesk/
Author: Jonathan Sick
Author-email: jonathansick@mac.com
License: UNKNOWN
Keywords: bibtex astronomy
Platform: UNKNOWN
Classifier: Development Status :: 5 - Production/Stable
Classifier: Intended Audience :: Science/Research
Classifier: License :: OSI Approved :: GNU General Public License v3 (GPLv3)
Classifier: Operating System :: MacOS :: MacOS X
Classifier: Topic :: Scientific/Engineering :: Astronomy
